paintcompiler/__init__.py
paintdecompiler/__init__.py
paintcompiler-0.3.4.dist-info/LICENSE
paintcompiler-0.3.4.dist-info/METADATA
paintcompiler-0.3.4.dist-info/WHEEL
paintcompiler-0.3.4.dist-info/entry_points.txt
paintcompiler-0.3.4.dist-info/top_level.txt
paintcompiler-0.3.4.dist-info/RECORD
