Metadata-Version: 2.1
Name: paintcompiler
Version: 0.3.4
Summary: Paint compiler for COLRv1 fonts
Author-email: Simon Cozens <simon@simon-cozens.org>
License: Apache Software License 2.0
License-File: LICENSE
Requires-Dist: fontTools >=4.37.3
